MANIFEST.in
fr_fiscal_templates.xml
fr_pcg_taxes.xml
fr_report.xml
fr_tax.xml
l10n_fr_view.xml
l10n_fr_wizard.xml
plan_comptable_general.xml
setup.py
./__init__.py
./__openerp__.py
./l10n_fr.py
./report/__init__.py
./report/base_report.py
./report/bilan_report.py
./report/compute_resultant_report.py
./wizard/__init__.py
./wizard/fr_report_bilan.py
./wizard/fr_report_compute_resultant.py
i18n/ar.po
i18n/bg.po
i18n/bs.po
i18n/ca.po
i18n/cs.po
i18n/da.po
i18n/de.po
i18n/es.po
i18n/es_AR.po
i18n/es_CR.po
i18n/es_MX.po
i18n/es_PY.po
i18n/es_VE.po
i18n/et.po
i18n/fr.po
i18n/gl.po
i18n/hr.po
i18n/hu.po
i18n/id.po
i18n/it.po
i18n/ko.po
i18n/ko_KO.po
i18n/l10n_fr.pot
i18n/lt.po
i18n/nl.po
i18n/nl_BE.po
i18n/oc.po
i18n/pl.po
i18n/pt.po
i18n/pt_BR.po
i18n/ro.po
i18n/ru.po
i18n/sl.po
i18n/sq.po
i18n/sr@latin.po
i18n/sv.po
i18n/tlh.po
i18n/tr.po
i18n/uk.po
i18n/vi.po
i18n/zh_CN.po
i18n/zh_TW.po
images/config_chart_l10n_fr.jpeg
images/l10n_fr_chart.jpeg
openerp_l10n_fr.egg-info/PKG-INFO
openerp_l10n_fr.egg-info/SOURCES.txt
openerp_l10n_fr.egg-info/dependency_links.txt
openerp_l10n_fr.egg-info/requires.txt
openerp_l10n_fr.egg-info/top_level.txt
report/bilan_report.rml
report/bilan_report.sxw
report/compute_resultant_report.rml
report/compute_resultant_report.sxw
security/ir.model.access.csv
static/src/img/icon.png
test/l10n_fr_report.yml
wizard/fr_report_bilan_view.xml
wizard/fr_report_compute_resultant_view.xml